multimodal/__init__.py
multimodal/__main__.py
multimodal/download.py
multimodal/registry.py
multimodal/utils.py
multimodal/commands/__init__.py
multimodal/commands/download.py
multimodal/commands/vqa_eval.py
multimodal/datasets/__init__.py
multimodal/datasets/clevr.py
multimodal/datasets/coco.py
multimodal/datasets/gqa.py
multimodal/datasets/lightning.py
multimodal/datasets/visualgenome.py
multimodal/datasets/vqa.py
multimodal/datasets/vqa1.py
multimodal/datasets/vqa_ce.py
multimodal/datasets/vqa_eval.py
multimodal/datasets/vqa_utils.py
multimodal/datasets/vqacp.py
multimodal/features/__init__.py
multimodal/features/bottomup-old.py
multimodal/features/bottomup.py
multimodal/features/coco_images.py
multimodal/features/features.py
multimodal/features/gqa.py
multimodal/features/gqa_features.py
multimodal/features/grid.py
multimodal/features/trash.py
multimodal/models/__init__.py
multimodal/models/lightning.py
multimodal/models/lxmert.py
multimodal/models/mcan.py
multimodal/models/mutan.py
multimodal/models/soho.py
multimodal/models/updown.py
multimodal/models/vilbert.py
multimodal/models/vilbert/__init__.py
multimodal/models/vilbert/test.py
multimodal/models/vilbert/utils.py
multimodal/models/vilbert/vilbert.py
multimodal/text/__init__.py
multimodal/text/basic_tokenizer.py
multimodal/text/wordembedding.py
multimodal-0.0.13.dist-info/LICENSE
multimodal-0.0.13.dist-info/METADATA
multimodal-0.0.13.dist-info/WHEEL
multimodal-0.0.13.dist-info/top_level.txt
multimodal-0.0.13.dist-info/RECORD
