Metadata-Version: 2.1
Name: multimodal
Version: 0.0.13
Summary: A collection of multimodal datasets multimodal for research.
Home-page: https://github.com/cdancette/multimodal
Author: Corentin Dancette
Author-email: corentin@cdancette.fr
License: UNKNOWN
Platform: UNKNOWN
Classifier: Programming Language :: Python :: 3
Classifier: License :: OSI Approved :: MIT License
Classifier: Operating System :: OS Independent
Requires-Python: >=3.6
Requires-Dist: numpy
Requires-Dist: tqdm
Requires-Dist: appdirs
Requires-Dist: torch (>=1)
Requires-Dist: pySmartDL
Requires-Dist: torchtext (>=0.6)
Requires-Dist: tables
Requires-Dist: Pillow (>=6)
Requires-Dist: torchvision
Requires-Dist: h5py
